behavysis_core/__init__.py
behavysis_core/constants.py
behavysis_core/df_classes/__init__.py
behavysis_core/df_classes/analyse_agg_df.py
behavysis_core/df_classes/analyse_combine_df.py
behavysis_core/df_classes/analyse_df.py
behavysis_core/df_classes/behav_df.py
behavysis_core/df_classes/bouts_df.py
behavysis_core/df_classes/df_mixin.py
behavysis_core/df_classes/features_df.py
behavysis_core/df_classes/keypoints_df.py
behavysis_core/mixins/__init__.py
behavysis_core/mixins/diagnostics_mixin.py
behavysis_core/mixins/io_mixin.py
behavysis_core/mixins/multiproc_mixin.py
behavysis_core/mixins/process_vid_mixin.py
behavysis_core/mixins/subproc_mixin.py
behavysis_core/pydantic_models/__init__.py
behavysis_core/pydantic_models/behav_classifier_configs.py
behavysis_core/pydantic_models/bouts.py
behavysis_core/pydantic_models/experiment_configs.py
behavysis_core/pydantic_models/pydantic_base_model.py
behavysis_core/pydantic_models/vid_metadata.py
behavysis_core-0.1.24.dist-info/LICENSE
behavysis_core-0.1.24.dist-info/METADATA
behavysis_core-0.1.24.dist-info/WHEEL
behavysis_core-0.1.24.dist-info/RECORD
