Metadata-Version: 2.1
Name: behavysis_core
Version: 0.1.24
Summary: Core functionality supporting the behavysis suite
Home-page: https://tlee08.github.io/behavysis_core/
License: LGPL-3.0-or-later
Author: BowenLab
Requires-Python: >=3.12,<3.13
Classifier: License :: OSI Approved :: GNU Lesser General Public License v3 or later (LGPLv3+)
Classifier: Programming Language :: Python :: 3
Classifier: Programming Language :: Python :: 3.12
Requires-Dist: natsort (>=8.4.0,<9.0.0)
Requires-Dist: numpy (>=1.26.4,<2.0.0)
Requires-Dist: opencv-python (>=4.9.0.80,<5.0.0.0)
Requires-Dist: pandas (>=2.2.2,<3.0.0)
Requires-Dist: pyarrow (>=18.0.0,<19.0.0)
Requires-Dist: pydantic (>=2.7.0,<3.0.0)
Requires-Dist: scipy (>=1.13.0,<2.0.0)
Requires-Dist: seaborn (>=0.13.2,<0.14.0)
Requires-Dist: tables (>=3.10.1,<4.0.0)
Requires-Dist: tqdm (>=4.30.0,<5.0.0)
Project-URL: Repository, https://github.com/tlee08/behavysis_core
